odoo/addons/pos_cashback_warning/README.rst
odoo/addons/pos_cashback_warning/__init__.py
odoo/addons/pos_cashback_warning/__manifest__.py
odoo/addons/pos_cashback_warning/i18n/fr.po
odoo/addons/pos_cashback_warning/i18n/pos_cashback_warning.pot
odoo/addons/pos_cashback_warning/readme/CONTRIBUTORS.rst
odoo/addons/pos_cashback_warning/readme/DESCRIPTION.rst
odoo/addons/pos_cashback_warning/static/description/icon.png
odoo/addons/pos_cashback_warning/static/description/index.html
odoo/addons/pos_cashback_warning/static/description/pos_cashback_warning.png
odoo/addons/pos_cashback_warning/static/src/js/screens.js
odoo/addons/pos_cashback_warning/static/src/xml/pos.xml
odoo/addons/pos_cashback_warning/views/templates.xml
odoo12_addon_pos_cashback_warning-12.0.1.0.2.dist-info/METADATA
odoo12_addon_pos_cashback_warning-12.0.1.0.2.dist-info/WHEEL
odoo12_addon_pos_cashback_warning-12.0.1.0.2.dist-info/top_level.txt
odoo12_addon_pos_cashback_warning-12.0.1.0.2.dist-info/RECORD
